clop.py
clop-0.2.8.dist-info/DESCRIPTION.rst
clop-0.2.8.dist-info/METADATA
clop-0.2.8.dist-info/RECORD
clop-0.2.8.dist-info/WHEEL
clop-0.2.8.dist-info/metadata.json
clop-0.2.8.dist-info/pbr.json
clop-0.2.8.dist-info/top_level.txt
