Metadata-Version: 2.0
Name: clop
Version: 0.2.8
Summary: A simple Command Line Option Processor
Home-page: https://github.com/a3n/clop
Author: Aaron
Author-email: a3n@justa3n.com
License: BSD
Keywords: option argument arg command line cmdline
Platform: UNKNOWN
Classifier: Development Status :: 4 - Beta
Classifier: Environment :: Console
Classifier: Intended Audience :: Developers
Classifier: License :: OSI Approved :: BSD License
Classifier: Natural Language :: English
Classifier: Operating System :: OS Independent
Classifier: Programming Language :: Python
Classifier: Topic :: Utilities
